{
  "order": [
    "1638995507af787164"
  ],
  "sections": {
    "1638995507af787164": {
      "type": "product__main",
      "blocks": {
        "badge_cGMpPb": {
          "type": "badge",
          "settings": {
            "icon": "check",
            "font_size": 13,
            "padding_x": 12,
            "padding_y": 6,
            "badge_text": "{{pdp_badge_text}}",
            "bg_opacity": 100,
            "badge_emoji": "{{pdp_badge_emoji}}",
            "font_weight": "700",
            "spacing_top": 10,
            "border_width": 0,
            "border_radius": 6,
            "badge_bg_color": "{{pdp_badge_bg_color}}",
            "border_opacity": 100,
            "letter_spacing": 1,
            "spacing_bottom": 10,
            "text_transform": "uppercase",
            "badge_font_color": "{{pdp_badge_font_color}}"
          }
        },
        "perks_j9yce9": {
          "type": "perks",
          "settings": {
            "label": "{{pdp_perks_label}}",
            "speed": 20,
            "perk_1": "{{pdp_perks_item_1}}",
            "perk_2": "{{pdp_perks_item_2}}",
            "perk_3": "{{pdp_perks_item_3}}",
            "perk_4": "{{pdp_perks_item_4}}",
            "perk_5": "{{pdp_perks_item_5}}",
            "header_bg": "{{pdp_perks_header_bg}}",
            "marquee_bg": "{{pdp_perks_marquee_bg}}",
            "header_text": "{{pdp_perks_header_text}}",
            "border_color": "#1a1a1a",
            "border_width": 1,
            "marquee_text": "{{pdp_perks_marquee_text}}",
            "border_radius": 10,
            "header_font_size": 15,
            "marquee_font_size": 15,
            "header_font_weight": "800",
            "marquee_font_weight": "500"
          }
        },
        "accordion_ERmP7y": {
          "type": "accordion",
          "settings": {
            "icon": "",
            "title": "",
            "content": "{{pdp_shipping_content}}",
            "position": "right",
            "enable_open": false,
            "spacing_top": 10,
            "color_border": "color__border-divider-1",
            "color_scheme": "btn--plain",
            "style_border": "",
            "spacing_bottom": 10
          }
        },
        "accordion_gJ6baw": {
          "type": "accordion",
          "settings": {
            "icon": "",
            "title": "",
            "content": "{{pdp_ingredients_content}}",
            "position": "right",
            "enable_open": false,
            "spacing_top": 10,
            "color_border": "color__border-divider-1",
            "color_scheme": "btn--plain",
            "style_border": "",
            "spacing_bottom": 10
          }
        },
        "checklist_QUhJj4": {
          "type": "checklist",
          "settings": {
            "item_1": "{{pdp_checklist_item_1}}",
            "item_2": "{{pdp_checklist_item_2}}",
            "item_3": "{{pdp_checklist_item_3}}",
            "item_4": "{{pdp_checklist_item_4}}",
            "item_5": "{{pdp_checklist_item_5}}",
            "check_color": "{{pdp_checklist_check_color}}",
            "spacing_top": 10,
            "spacing_bottom": 10,
            "value_prop_tag": "{{pdp_checklist_value_tag}}",
            "value_prop_text": "{{pdp_checklist_value_text}}"
          }
        },
        "variant_cards_JhQkVx": {
          "type": "variant_cards",
          "settings": {
            "option_name": "{{pdp_variant_option_name}}",
            "spacing_top": 10,
            "best_badge_bg": "{{pdp_best_badge_bg}}",
            "show_per_unit": true,
            "spacing_bottom": 10,
            "desktop_columns": "3",
            "popular_badge_bg": "{{pdp_popular_badge_bg}}",
            "free_shipping_threshold": "{{pdp_free_shipping_threshold}}"
          }
        },
        "moast_carousel_eeK4GX": {
          "type": "shopify://apps/moast/blocks/carousel/1ac7547b-5443-446c-868c-7fab4566ee16",
          "settings": {
            "feed": "default",
            "border": 0,
            "header": "",
            "dynamic": false,
            "alignment": "center",
            "custom_css": "",
            "feed_usage": "back_up",
            "float_size": "medium",
            "pagination": "below",
            "slide_size": "100",
            "slide_type": "cards",
            "padding_top": 40,
            "aspect_ratio": "vertical",
            "border_color": "linear-gradient(to right, #833ab4, #fd1d1d, #fcb045)",
            "click_action": "fullscreen",
            "autoplay_mode": "none",
            "product_cards": "none",
            "show_captions": false,
            "slide_spacing": 16,
            "float_location": "bottom_right",
            "slide_rounding": "20",
            "autoscroll_duration": 0
          }
        },
        "123fd04c-91f3-4248-a65a-614e2f64fdeb": {
          "type": "description",
          "settings": {
            "position": "right",
            "enable_open": true,
            "spacing_top": 10,
            "color_border": "color__border-divider-1",
            "color_scheme": "btn--plain",
            "style_border": "",
            "spacing_bottom": 10,
            "enable_accordion": true,
            "layout_x_alignment": "left"
          }
        },
        "62c29cd6-a0b5-4f8b-86c0-a48660869d22": {
          "type": "price",
          "settings": {
            "font": "type__nav",
            "position": "right",
            "spacing_top": 0,
            "color_border": "color__border-divider-1",
            "color_scheme": "color__bg-transparent",
            "style_border": "",
            "spacing_bottom": 10
          }
        },
        "853ae7f0-85c9-45dc-8326-6e4044bcf5e5": {
          "type": "title",
          "settings": {
            "content": "",
            "position": "right",
            "enable_sku": false,
            "enable_type": false,
            "spacing_top": 10,
            "color_border": "color__border-divider-1",
            "color_scheme": "color__bg-transparent",
            "style_border": "",
            "enable_badges": true,
            "enable_vendor": false,
            "savings_badge": "none",
            "spacing_bottom": 10
          }
        },
        "b78b560b-e1c2-428d-ad73-fb5f8aac6d53": {
          "type": "add",
          "settings": {
            "content": "",
            "position": "right",
            "spacing_top": 20,
            "color_border": "color__border-divider-1",
            "color_button": "btn",
            "color_scheme": "color__bg-transparent",
            "style_border": "",
            "spacing_bottom": 20,
            "enable_quantity": false,
            "enable_dynamic_checkout": false,
            "enable_gift_card_recipient": false
          }
        },
        "b78b560b-e1c2-428d-ad73-fb5f8aac6d58": {
          "type": "options",
          "settings": {
            "position": "right",
            "spacing_top": 20,
            "color_border": "color__border-divider-1",
            "color_scheme": "color__bg-transparent",
            "style_border": "",
            "spacing_bottom": 0
          }
        }
      },
      "settings": {
        "enable_alt": false,
        "zoom_level": "scale-[1.5]",
        "enable_zoom": true,
        "media_ratio": "aspect-[1/1]",
        "spacing_top": 20,
        "color_scheme": "color__bg-body",
        "enable_ratio": true,
        "media_border": "",
        "enable_arrows": false,
        "indicator_type": "standard",
        "spacing_bottom": 0,
        "media_grid_size": 1,
        "color_background": "#ffffff",
        "enable_color_fade": false,
        "enable_main_margin": true,
        "media_color_scheme": "color__bg-shade-2 color__text",
        "enable_media_margin": true,
        "layout_column_width": 50,
        "media_gallery_style": "grid",
        "media_object_sizing": "cover",
        "enable_default_plans": false,
        "enable_header_overlap": false,
        "enable_variant_images": false,
        "enable_default_variant": true,
        "media_gallery_position": "left",
        "media_slider_size_mobile": 100,
        "media_slider_size_desktop": 100,
        "enable_default_selling_plan_widget": false
      },
      "block_order": [
        "badge_cGMpPb",
        "853ae7f0-85c9-45dc-8326-6e4044bcf5e5",
        "checklist_QUhJj4",
        "62c29cd6-a0b5-4f8b-86c0-a48660869d22",
        "variant_cards_JhQkVx",
        "b78b560b-e1c2-428d-ad73-fb5f8aac6d58",
        "perks_j9yce9",
        "b78b560b-e1c2-428d-ad73-fb5f8aac6d53",
        "123fd04c-91f3-4248-a65a-614e2f64fdeb",
        "accordion_gJ6baw",
        "accordion_ERmP7y",
        "moast_carousel_eeK4GX"
      ]
    }
  }
}
